rbac_rag/__init__.py
rbac_rag/_types.py
rbac_rag/rbac_manager.py
rbac_rag/roles.py
rbac_rag/secure_rag.py
rbac_rag/utils.py
rbac_rag-1.0.0.dist-info/LICENSE
rbac_rag-1.0.0.dist-info/METADATA
rbac_rag-1.0.0.dist-info/WHEEL
rbac_rag-1.0.0.dist-info/entry_points.txt
rbac_rag-1.0.0.dist-info/top_level.txt
rbac_rag-1.0.0.dist-info/RECORD
