Metadata-Version: 2.1
Name: rbac_rag
Version: 1.0.0
Summary: Simple, Safe, and Secure RAG from Haize Labs
Requires-Python: >=3.10
License-File: LICENSE
Requires-Dist: openai
Requires-Dist: pymongo
Requires-Dist: requests
Requires-Dist: python-dotenv
Requires-Dist: pydantic
Requires-Dist: numpy
